{
    "$schema": "https://schema.management.azure.com/schemas/2015-01-01/deploymentParameters.json#",
    "contentVersion": "1.0.0.0",
    "parameters": {
        "location": {
            "value": "switzerlandnorth"
        },
        "networkInterfaceName": {
            "value": "crdwsr0200"
        },
        "subnetName": {
            "value": "sub-middleware-01"
        },
        "virtualNetworkId": {
            "value": "/subscriptions/4ecf3830-c880-4410-9c3b-21919c807bad/resourceGroups/rg-cis-prod-network-01/providers/Microsoft.Network/virtualNetworks/vnet-prod-sn-01"
        },
        "virtualMachineName": {
            "value": "crdwsr0200"
        },
        "virtualMachineComputerName": {
            "value": "crdwsr0200"
        },
        "virtualMachineRG": {
            "value": "rg-crd-prod-ptc-01"
        },
        "osDiskType": {
            "value": "StandardSSD_LRS"
        },
        "osDiskDeleteOption": {
            "value": "Detach"
        },
        "virtualMachineSize": {
            "value": "Standard_D3s_v2"
        },
        "nicDeleteOption": {
            "value": "Detach"
        },
        "adminUsername": {
            "value": "ldmsosd"
        },
        "adminPassword": {
            "value": "Newsetup1234"
        },
        "patchMode": {
            "value": "Manual"
        },
        "enableHotpatching": {
            "value": false
        },
        "diagnosticsStorageAccountName": {
            "value": "stproddiagnostic0001"
        },
        "diagnosticsStorageAccountId": {
            "value": "/subscriptions/4ecf3830-c880-4410-9c3b-21919c807bad/resourceGroups/rg-cis-prod-storage-01/providers/Microsoft.Storage/storageAccounts/stproddiagnostic0001"
        }
    }
}